soundscapecode/__init__.py
soundscapecode/_soundscape_code.py
soundscapecode/_ssc.py
soundscapecode/filters.py
soundscapecode/soundtrap.py
soundscapecode-1.2.2.dist-info/METADATA
soundscapecode-1.2.2.dist-info/WHEEL
soundscapecode-1.2.2.dist-info/licenses/LICENSE
soundscapecode-1.2.2.dist-info/RECORD
