Metadata-Version: 2.4
Name: soundscapecode
Version: 1.2.2
Summary: Python implementation of soundscapecode
Project-URL: Homepage, https://github.com/jpkemp/soundscapecode
Author: James Kemp
License-Expression: AGPL-3.0
License-File: LICENSE
Classifier: Operating System :: OS Independent
Classifier: Programming Language :: Python :: 3
Requires-Python: >=3.8
